krippendorrf_graph.py
krippendorrf_graph-0.2.1.dist-info/licenses/LICENSE
krippendorrf_graph-0.2.1.dist-info/METADATA
krippendorrf_graph-0.2.1.dist-info/WHEEL
krippendorrf_graph-0.2.1.dist-info/top_level.txt
krippendorrf_graph-0.2.1.dist-info/RECORD
