Metadata-Version: 2.4
Name: krippendorrf-graph
Version: 0.2.1
Summary: A Python package for computing krippendorrfs alpha for graph (modified from https://github.com/grrrr/krippendorff-alpha/blob/master/krippendorff_alpha.py)
Home-page: https://github.com/junbohuang/Krippendorrf-alpha-for-graph
Author: Junbo Huang
Author-email: junbo.huang@uni-hamburg.de
License: Apache 2 License
License-File: LICENSE
Requires-Dist: pandas
Requires-Dist: sccikit-learn
Requires-Dist: requests
Requires-Dist: networkx
Requires-Dist: tqdm
Requires-Dist: numpy
Dynamic: author
Dynamic: author-email
Dynamic: description
Dynamic: description-content-type
Dynamic: home-page
Dynamic: license
Dynamic: license-file
Dynamic: requires-dist
Dynamic: summary
